iosacal/__init__.py
iosacal/cli.py
iosacal/core.py
iosacal/hpd.py
iosacal/plot.py
iosacal/spd.py
iosacal/text.py
iosacal/data/intcal04.14c
iosacal/data/intcal09.14c
iosacal/data/intcal13.14c
iosacal/data/intcal20.14c
iosacal/data/intcal98.14c
iosacal/data/marine04.14c
iosacal/data/marine09.14c
iosacal/data/marine13.14c
iosacal/data/marine20.14c
iosacal/data/marine98.14c
iosacal/data/shcal04.14c
iosacal/data/shcal13.14c
iosacal/data/shcal20.14c
iosacal-0.6.0.dist-info/LICENSE
iosacal-0.6.0.dist-info/METADATA
iosacal-0.6.0.dist-info/WHEEL
iosacal-0.6.0.dist-info/entry_points.txt
iosacal-0.6.0.dist-info/top_level.txt
iosacal-0.6.0.dist-info/RECORD
