Metadata-Version: 2.1
Name: iosacal
Version: 0.6.0
Summary: "IOSACal is a radiocarbon (14C) calibration program"
Home-page: http://c14.iosa.it
Author: "Stefano Costa"
Author-email: steko@iosa.it
Maintainer: "Stefano Costa"
Maintainer-email: steko@iosa.it
Keywords: radiocarbon,calibration
Classifier: Development Status :: 4 - Beta
Classifier: Environment :: Console
Classifier: Intended Audience :: Science/Research
Classifier: Operating System :: OS Independent
Classifier: Programming Language :: Python :: 3 :: Only
Classifier: Topic :: Scientific/Engineering
Requires-Python: ~=3.8
License-File: LICENSE
Requires-Dist: numpy (>=1.18.0)
Requires-Dist: scipy (>=1.1.0)
Requires-Dist: matplotlib (~=3.0)
Requires-Dist: click (~=8.0)
Provides-Extra: test
Requires-Dist: pytest (~=6.2) ; extra == 'test'
Requires-Dist: tox (~=3.2) ; extra == 'test'
